tlcloud/__init__.py
tlcloud/geo.py
tlcloud-1.1.dist-info/LICENSE
tlcloud-1.1.dist-info/METADATA
tlcloud-1.1.dist-info/WHEEL
tlcloud-1.1.dist-info/top_level.txt
tlcloud-1.1.dist-info/RECORD
